jingo/__init__.py
jingo/ext.py
jingo/helpers.py
jingo/monkey.py
jingo-0.9.0.dist-info/DESCRIPTION.rst
jingo-0.9.0.dist-info/METADATA
jingo-0.9.0.dist-info/RECORD
jingo-0.9.0.dist-info/WHEEL
jingo-0.9.0.dist-info/metadata.json
jingo-0.9.0.dist-info/top_level.txt
